[{"track_name": "You Don't Know How Lucky You Are", "track_url": "https://open.spotify.com/track/7L4w1yQnlhqo4oUjpW53wz", "track_uri": "spotify:track:7L4w1yQnlhqo4oUjpW53wz", "album_name": "Dear", "release_date": "01/01/2010", "artists": ["Keaton Henson"], "image": "https://i.scdn.co/image/ab67616d00001e02bc1eea2d47100a4498661df7"}, {"track_name": "Something - Audiotree Live Version", "track_url": "https://open.spotify.com/track/1If41CkI9tPLQ3airoOAKl", "track_uri": "spotify:track:1If41CkI9tPLQ3airoOAKl", "album_name": "Julien Baker on Audiotree Live", "release_date": "22/10/2015", "artists": ["Julien Baker"], "image": "https://i.scdn.co/image/ab67616d00001e02d84986b09bb390a847d6cf6f"}, {"track_name": "Don't You Remember", "track_url": "https://open.spotify.com/track/1CRtJS94Hq3PbBZT9LuF90", "track_uri": "spotify:track:1CRtJS94Hq3PbBZT9LuF90", "album_name": "21", "release_date": "24/01/2011", "artists": ["Adele"], "image": "https://i.scdn.co/image/ab67616d00001e02fb7eedd9877b0c60597ef3e5"}, {"track_name": "Paper Rings", "track_url": "https://open.spotify.com/track/4y5bvROuBDPr5fuwXbIBZR", "track_uri": "spotify:track:4y5bvROuBDPr5fuwXbIBZR", "album_name": "Lover", "release_date": "23/08/2019", "artists": ["Taylor Swift"], "image": "https://i.scdn.co/image/ab67616d00001e02e787cffec20aa2a396a61647"}, {"track_name": "Chaand Baaliyan", "track_url": "https://open.spotify.com/track/0snQrp1VaY5Pj1YIHRJpRJ", "track_uri": "spotify:track:0snQrp1VaY5Pj1YIHRJpRJ", "album_name": "Chaand Baaliyan", "release_date": "28/03/2020", "artists": ["Aditya A"], "image": "https://i.scdn.co/image/ab67616d00001e02ec4ecaa0fcf68c0966f21514"}, {"track_name": "Under Your Spell", "track_url": "https://open.spotify.com/track/2cSRuejq6DU9U6OkSmUw17", "track_uri": "spotify:track:2cSRuejq6DU9U6OkSmUw17", "album_name": "Desire", "release_date": "17/03/2009", "artists": ["Desire"], "image": "https://i.scdn.co/image/ab67616d00001e020b52377b2466d5f5552800ae"}, {"track_name": "Keep It Light", "track_url": "https://open.spotify.com/track/2BUP8KOWDlCsdEV8DJPQQn", "track_uri": "spotify:track:2BUP8KOWDlCsdEV8DJPQQn", "album_name": "Thats What They All Say", "release_date": "11/12/2020", "artists": ["Jack Harlow"], "image": "https://i.scdn.co/image/ab67616d00001e02aeb14ead136118a987246b63"}, {"track_name": "Love Walked In", "track_url": "https://open.spotify.com/track/71D2G19A2i5BYgTC31p23j", "track_uri": "spotify:track:71D2G19A2i5BYgTC31p23j", "album_name": "Backstreet Symphony", "release_date": "26/02/1990", "artists": ["Thunder"], "image": "https://i.scdn.co/image/ab67616d00001e02fd9ec5e71e0eea55003f60d5"}, {"track_name": "So Far", "track_url": "https://open.spotify.com/track/4WQytMpyTMjzMW30wvVQid", "track_uri": "spotify:track:4WQytMpyTMjzMW30wvVQid", "album_name": "So Far", "release_date": "25/06/2020", "artists": ["Karan Aujla"], "image": "https://i.scdn.co/image/ab67616d00001e02563f55554ffa381d564a834c"}, {"track_name": "Between The Bars", "track_url": "https://open.spotify.com/track/52Bg6oaos7twR7IUtEpqcE", "track_uri": "spotify:track:52Bg6oaos7twR7IUtEpqcE", "album_name": "Either/Or", "release_date": "25/02/1997", "artists": ["Elliott Smith"], "image": "https://i.scdn.co/image/ab67616d00001e02ea7ac80765aa4549d18a27b9"}, {"track_name": "Remember To Forget Me", "track_url": "https://open.spotify.com/track/30zjD8uAoLLckluGf0PNV6", "track_uri": "spotify:track:30zjD8uAoLLckluGf0PNV6", "album_name": "NINE", "release_date": "20/09/2019", "artists": ["blink-182"], "image": "https://i.scdn.co/image/ab67616d00001e02198542728b101474c4afe0a1"}, {"track_name": "Non Believer", "track_url": "https://open.spotify.com/track/0V62AlQ6Lqy6xPK1sZTLD5", "track_uri": "spotify:track:0V62AlQ6Lqy6xPK1sZTLD5", "album_name": "Truth Is a Beautiful Thing (Deluxe)", "release_date": "09/06/2017", "artists": ["London Grammar"], "image": "https://i.scdn.co/image/ab67616d00001e02c380c82f7dfca69200a92dc2"}, {"track_name": "100", "track_url": "https://open.spotify.com/track/19zpbpzmNDRJdlSEAKMBrS", "track_uri": "spotify:track:19zpbpzmNDRJdlSEAKMBrS", "album_name": "100", "release_date": "10/10/2019", "artists": ["Lxst", "Suigeneris"], "image": "https://i.scdn.co/image/ab67616d00001e02bc8273185ad0da399b51468d"}, {"track_name": "Red (Taylor's Version)", "track_url": "https://open.spotify.com/track/4OAuvHryIVv4kMDNSLuPt6", "track_uri": "spotify:track:4OAuvHryIVv4kMDNSLuPt6", "album_name": "Red (Taylor's Version)", "release_date": "12/11/2021", "artists": ["Taylor Swift"], "image": "https://i.scdn.co/image/ab67616d00001e02318443aab3531a0558e79a4d"}, {"track_name": "Work", "track_url": "https://open.spotify.com/track/50yvvXV8oUAhW1lPAqlFQQ", "track_uri": "spotify:track:50yvvXV8oUAhW1lPAqlFQQ", "album_name": "Futures", "release_date": "19/10/2004", "artists": ["Jimmy Eat World"], "image": "https://i.scdn.co/image/ab67616d00001e025779a43af09192de496b1b66"}]